labeled_mask/__init__.py
labeled_mask/mask_manager.py
labeled_mask/simple_slicer.py
labeled_mask-0.1.1.dist-info/WHEEL
labeled_mask-0.1.1.dist-info/METADATA
labeled_mask-0.1.1.dist-info/RECORD
