Metadata-Version: 2.1
Name: labeled-mask
Version: 0.1.1
Summary: Provide interface of tagged mask that make easy to squeeze target data from array
License: MIT
Author: wwwshwww
Author-email: www.shinderu.www@gmail.com
Requires-Python: >=2.7
Classifier: License :: OSI Approved :: MIT License
Classifier: Programming Language :: Python :: 2
Classifier: Programming Language :: Python :: 2.7
Classifier: Programming Language :: Python :: 3
Classifier: Programming Language :: Python :: 3.4
Classifier: Programming Language :: Python :: 3.5
Classifier: Programming Language :: Python :: 3.6
Classifier: Programming Language :: Python :: 3.7
Classifier: Programming Language :: Python :: 3.8
Classifier: Programming Language :: Python :: 3.9
Requires-Dist: numpy (>=1.16,<2.0); python_version >= "2.7.0" and python_version < "2.8.0"
